commit_with_ai.py
commit_with_ai-1.0.1.dist-info/METADATA
commit_with_ai-1.0.1.dist-info/WHEEL
commit_with_ai-1.0.1.dist-info/entry_points.txt
commit_with_ai-1.0.1.dist-info/licenses/LICENSE
commit_with_ai-1.0.1.dist-info/RECORD
