Metadata-Version: 2.4
Name: commit-with-ai
Version: 1.0.1
Summary: AI-powered git commit message generator using Gemini API
Project-URL: Homepage, https://github.com/chenwei791129/commit-with-ai
Project-URL: Repository, https://github.com/chenwei791129/commit-with-ai
Project-URL: Bug Tracker, https://github.com/chenwei791129/commit-with-ai/issues
Project-URL: Changelog, https://github.com/chenwei791129/commit-with-ai/releases
Author-email: Chen-Wei Sun <chenwei791129@livemail.tw>
License: MIT
License-File: LICENSE
Keywords: ai,cli,commit,conventional-commits,gemini,git
Classifier: Development Status :: 4 - Beta
Classifier: Environment :: Console
Classifier: Intended Audience :: Developers
Classifier: License :: OSI Approved :: MIT License
Classifier: Operating System :: POSIX
Classifier: Programming Language :: Python :: 3
Classifier: Programming Language :: Python :: 3.10
Classifier: Programming Language :: Python :: 3.11
Classifier: Programming Language :: Python :: 3.12
Classifier: Programming Language :: Python :: 3.13
Classifier: Topic :: Software Development :: Version Control :: Git
Classifier: Topic :: Utilities
Requires-Python: >=3.10
Requires-Dist: google-genai>=1.60.0
Provides-Extra: dev
Requires-Dist: pytest>=8.0.0; extra == 'dev'
Requires-Dist: ruff>=0.8.0; extra == 'dev'
